LogseqMarkdownParser/__init__.py
LogseqMarkdownParser/__main__.py
LogseqMarkdownParser/blocks.py
LogseqMarkdownParser/pages.py
LogseqMarkdownParser-3.3.dist-info/LICENSE
LogseqMarkdownParser-3.3.dist-info/METADATA
LogseqMarkdownParser-3.3.dist-info/WHEEL
LogseqMarkdownParser-3.3.dist-info/entry_points.txt
LogseqMarkdownParser-3.3.dist-info/top_level.txt
LogseqMarkdownParser-3.3.dist-info/RECORD
