Metadata-Version: 2.1
Name: LogseqMarkdownParser
Version: 3.3
Summary: parse logseq markdown text with easy access to properties, hierarchy, TODO etc
Home-page: https://github.com/thiswillbeyourgithub/LogseqMarkdownParser
Author: thiswillbeyourgithub
Keywords: Logseq,PKM,Markdown,parsing,parser,properties,block,text
Classifier: License :: OSI Approved :: GNU General Public License v3 or later (GPLv3+)
Classifier: Programming Language :: Python
Classifier: Programming Language :: Python :: 3
Requires-Python: >=3.9
License-File: LICENSE
Requires-Dist: fire >=0.5.0
Requires-Dist: rtoml >=0.11.0
Requires-Dist: uuid6 >=2024.7.10
Provides-Extra: beartype
Requires-Dist: beartype ; extra == 'beartype'
